lazyreadme/__init__.py
lazyreadme/__main__.py
lazyreadme/cli/__init__.py
lazyreadme/cli/interface.py
lazyreadme/templates/sections.py
lazyreadme/utils/console.py
lazyreadme-1.0.6.dist-info/licenses/LICENSE
lazyreadme-1.0.6.dist-info/METADATA
lazyreadme-1.0.6.dist-info/WHEEL
lazyreadme-1.0.6.dist-info/entry_points.txt
lazyreadme-1.0.6.dist-info/top_level.txt
lazyreadme-1.0.6.dist-info/RECORD
