Metadata-Version: 2.4
Name: lazyreadme
Version: 1.0.6
Summary: Generate README.md files automatically
Author: Raphael Elias
Author-email: Raphael <raphaeleliass@outlook.com>
License: MIT
Requires-Python: >=3.6
License-File: LICENSE
Requires-Dist: questionary>=2.0.1
Requires-Dist: colorama>=0.4.6
Dynamic: author
Dynamic: license-file
Dynamic: requires-python
